Metadata-Version: 1.0
Name: test-by-prem
Version: 0.1
Summary: package for clothing, 
Home-page: UNKNOWN
Author: UNKNOWN
Author-email: UNKNOWN
License: UNKNOWN
Platform: UNKNOWN
